sdif_db/__init__.py
sdif_db/database.py
sdif_db/schema.py
sdif_db/utils.py
sdif_db-0.7.3.dist-info/LICENSE
sdif_db-0.7.3.dist-info/METADATA
sdif_db-0.7.3.dist-info/WHEEL
sdif_db-0.7.3.dist-info/entry_points.txt
sdif_db-0.7.3.dist-info/RECORD
